sdh.cdn-1.1.9-py3.8-nspkg.pth
sdh/cdn/__init__.py
sdh/cdn/apps.py
sdh/cdn/storages.py
sdh/cdn/management/commands/migrate_images.py
sdh/cdn/templatetags/__init__.py
sdh/cdn/templatetags/sdh_cdn.py
sdh.cdn-1.1.9.dist-info/LICENSE
sdh.cdn-1.1.9.dist-info/METADATA
sdh.cdn-1.1.9.dist-info/WHEEL
sdh.cdn-1.1.9.dist-info/eager_resources.txt
sdh.cdn-1.1.9.dist-info/namespace_packages.txt
sdh.cdn-1.1.9.dist-info/top_level.txt
sdh.cdn-1.1.9.dist-info/RECORD
